wiq/__init__.py
wiq/__version__.py
wiq/api.py
wiq/exceptions.py
wiq/models/__init__.py
wiq/models/balance.py
wiq/models/order.py
wiq/models/service.py
wiq-0.1.2.dist-info/METADATA
wiq-0.1.2.dist-info/WHEEL
wiq-0.1.2.dist-info/top_level.txt
wiq-0.1.2.dist-info/RECORD
