Metadata-Version: 2.1
Name: wiq
Version: 0.1.2
Summary: Asynchronous module for working with the cheating wiq.ru API
Author: VoXDoX
Author-email: 1voxdox1@gmail.com
Project-URL: TG Channel, https://t.me/AsyncModules
Project-URL: Github, https://github.com/VoXDoX/wiq
Keywords: wiq,wiq api,api wiq
Requires-Python: >=3.7
Requires-Dist: setuptools (~=65.5.1)
Requires-Dist: certifi (~=2022.9.24)
Requires-Dist: aiohttp (~=3.8.3)
Requires-Dist: pydantic (~=1.10.7)
